gb_mess_server-0.1.0.data/scripts/server_run
server/__init__.py
server/encryption.py
server/server.py
server/server/__init__.py
server/server/add_user.py
server/server/db_server.py
server/server/server_gui.py
server/services/__init__.py
server/services/actions.py
server/services/status_code.py
server/test/__init__.py
server/test/test_client.py
server/test/test_server.py
gb_mess_server-0.1.0.dist-info/METADATA
gb_mess_server-0.1.0.dist-info/WHEEL
gb_mess_server-0.1.0.dist-info/top_level.txt
gb_mess_server-0.1.0.dist-info/RECORD
