Metadata-Version: 2.1
Name: gb-mess-server
Version: 0.1.0
Summary: Messenger for Server
Home-page: UNKNOWN
Author: Nikita Savchenko
Author-email: nikita.savchenko.developer@gmail.com
License: UNKNOWN
Platform: UNKNOWN
Requires-Dist: PyQt5
Requires-Dist: sqlalchemy
Requires-Dist: pycryptodome
Requires-Dist: pycryptodomex
